README.md
notiforward.py
setup.py
notiforward.egg-info/PKG-INFO
notiforward.egg-info/SOURCES.txt
notiforward.egg-info/dependency_links.txt
notiforward.egg-info/entry_points.txt
notiforward.egg-info/requires.txt
notiforward.egg-info/top_level.txt