Metadata-Version: 2.1
Name: notiforward
Version: 0.0.3
Summary: Forward DBUS notifications
Home-page: https://gitlab.com/rendaw/notiforward
Author: rendaw
License: MIT
Download-URL: https://gitlab.com/rendaw/notiforward/-/archive/v0.0.3/notiforward-v0.0.3.tar.gz
Platform: UNKNOWN
